{
  "id": "gm/loot/chest-lock",
  "title": "Chest Locks",
  "pillar": "gm",
  "tags": [
    "fantasy"
  ],
  "credits": [
    {
      "source": "r/d100",
      "url": "https://www.reddit.com/r/d100/"
    },
    {
      "source": "r/BehindTheTables",
      "url": "https://www.reddit.com/r/BehindTheTables/"
    },
    {
      "source": "r/DnDBehindTheScreen",
      "url": "https://www.reddit.com/r/DnDBehindTheScreen/"
    },
    {
      "source": "DnDSpeak",
      "url": "http://dndspeak.com/"
    }
  ],
  "entries": [
    "padlock",
    "internal mechanism lock",
    "combination lock",
    "puzzle lock",
    "password lock",
    "hidden lock mechanism",
    "biometric lock with fingerprint recognition",
    "voice-activated lock with a secret passphrase",
    "retinal scanner that requires specific eye identification",
    "magical sigil lock, requiring the correct sequence of runes to be traced",
    "time-based lock that opens only at a specific astrological alignment",
    "musical lock, requiring a particular melody to be played on a set of keys",
    "ancient mechanical lock with intricate gears and moving parts",
    "enchanted riddle lock, requiring the solution to a cryptic puzzle",
    "magnetic lock, requiring a specific magnetic key to activate",
    "heat-sensitive lock, requiring the chest to be warmed to a certain temperature",
    "cold-sensitive lock, requiring the chest to be chilled to a certain degree",
    "light-based lock, needing a specific pattern of light to be projected onto it",
    "shadow puzzle lock, requiring the correct arrangement of objects to cast specific shadows",
    "clockwork lock, needing the hands of a clock to be set at a precise time",
    "celestial lock, aligning with the positions of celestial bodies in the sky",
    "water-based lock, reacting to the flow of water or the level of liquid",
    "fire puzzle lock, requiring specific torches to be lit in the correct sequence",
    "wind-powered lock, needing a continuous flow of air to activate",
    "gemstone combination lock, requiring certain precious gems to be inserted in order",
    "steampunk-style lock, combining mechanical gears with retro-futuristic elements",
    "mechanical keypad lock, needing the correct sequence of buttons to be pressed",
    "engraved lock, requiring a particular pattern or design to be traced",
    "enchanted lock that can only be opened by moonlight or sunlight",
    "mirror-based lock, needing light to be reflected in a specific manner",
    "invisible lock, where the mechanism is hidden and must be sensed through touch",
    "crystal lock, requiring a certain crystal to be inserted to unlock the chest",
    "gravity-based lock, responding to the positioning of the chest in space",
    "emblem lock, requiring the placement of specific symbols in the correct positions",
    "animal-shaped lock, where different animal figurines must be turned to open",
    "magical lock with shifting symbols, requiring the right sequence to be selected",
    "wooden combination lock, with notches and grooves aligning in a particular way",
    "astronomical lock, aligning with astronomical events or constellations",
    "morse code lock, needing a sequence of taps or sounds to be transmitted",
    "invisible ink lock, requiring the application of a specific substance to reveal the code",
    "astral projection lock, where the opener must enter a spiritual realm to unlock",
    "liquid metal lock, with the mechanism formed from a shape-shifting metal",
    "moon phase lock, aligning with the current phase of the moon",
    "dial lock with movable rings, requiring specific symbols to align",
    "alphabet lock, requiring certain letters to be pressed in order",
    "time-based combination lock, requiring specific actions to be performed at precise intervals",
    "wind chime lock, requiring the right chimes to be triggered in harmony",
    "holographic lock, requiring the projection of specific holographic images",
    "gemstone puzzle lock, needing specific gems to be inserted in a specific order",
    "levitation lock, requiring the chest to be lifted using levitation magic",
    "magnetic puzzle lock, where pieces must be aligned using magnetic forces",
    "color-based lock, requiring certain colors to be displayed in a particular pattern",
    "night sky lock, aligning with the position of stars and planets in the night sky",
    "chessboard lock, requiring specific chess pieces to be moved in a certain sequence",
    "crystal pendulum lock, with the pendulum swinging in a specific pattern to unlock",
    "zodiac lock, aligning with the current position of the zodiac signs",
    "fire and ice lock, needing specific flames and ice sources to activate",
    "shape-shifting lock, with the mechanism changing form upon touch",
    "clockwork puzzle lock, with gears that must be rotated to fit in the right positions",
    "elemental lock, requiring the use of elemental powers to unlock",
    "music box lock, where a particular tune must be played on a music box to unlock",
    "night and day lock, with two different mechanisms activated at different times",
    "mirror maze lock, needing the opener to navigate through a maze of mirrors",
    "constellation lock, aligning with the current arrangement of constellations",
    "glyphic lock, requiring specific glyphs to be pressed in the correct sequence",
    "waterwheel lock, requiring the chest to be turned like a waterwheel to unlock",
    "planetary lock, aligning with the current positions of the planets",
    "firefly lock, requiring the correct fireflies to be captured and placed in a container",
    "morphing lock, with the mechanism changing shape and configuration randomly",
    "wind puzzle lock, requiring the correct gusts of wind to be generated",
    "ancient language lock, needing the correct phrases or words to be spoken or written",
    "holographic keypad lock, with a holographic display showing changing patterns",
    "star map lock, aligning with the current arrangement of stars",
    "frozen lock, requiring the chest to be frozen in ice to activate",
    "gemstone constellation lock, needing specific gems to be arranged like constellations",
    "alchemy lock, requiring the correct alchemical reagents to be mixed together",
    "mathematical puzzle lock, requiring specific equations or formulas to be solved",
    "time sandglass lock, needing sand to be poured in a specific time frame",
    "phoenix lock, requiring the chest to be exposed to fire before unlocking",
    "bio-organic lock, responding to the touch of a living organism",
    "clock tower lock, requiring the chest to be placed in a specific clock tower",
    "ancient tablet lock, needing the correct sequence of tablet rotations",
    "ethereal lock, requiring the opener to shift into an ethereal form to unlock",
    "memory lock, with the mechanism activated by specific memories or experiences",
    "gear puzzle lock, with interlocking gears that must be set in the right positions",
    "crystal prism lock, requiring light to be refracted in a specific manner",
    "sundial lock, aligning with the current position of the sun's shadow",
    "water puzzle lock, requiring the flow of water to activate certain mechanisms",
    "magnetic pendulum lock, with the pendulum influencing the magnetic mechanism",
    "ancient hieroglyph lock, needing specific hieroglyphs to be pressed in order",
    "sound-based lock, requiring specific musical notes to be played or sung",
    "living vine lock, with vines that must be guided and woven to unlock",
    "alchemy circle lock, requiring the correct arrangement of alchemical symbols",
    "time warp lock, with the mechanism activating during specific temporal distortions",
    "fire maze lock, needing the opener to navigate through a maze of fire barriers",
    "wind compass lock, aligning with the direction of the wind",
    "tide-based lock, aligning with the current tidal patterns",
    "runic lock, needing the correct runic sequence to be traced",
    "shadow clock lock, with the shadow of an object indicating the correct time to unlock",
    "solar beam lock, requiring mirrors to align and reflect sunlight onto the mechanism",
    "living statue lock, with statues that must be moved into specific positions",
    "alchemy cauldron lock, requiring the correct ingredients to be mixed in a cauldron",
    "heartbeat lock, with the mechanism activated by the touch of a living being's heartbeat",
    "gong lock, requiring specific gongs to be struck in the right order",
    "crystal prism lock, requiring light to be refracted in a specific manner",
    "sundial lock, aligning with the current position of the sun's shadow",
    "water puzzle lock, requiring the flow of water to activate certain mechanisms",
    "magnetic pendulum lock, with the pendulum influencing the magnetic mechanism",
    "ancient hieroglyph lock, needing specific hieroglyphs to be pressed in order",
    "sound-based lock, requiring specific musical notes to be played or sung",
    "living vine lock, with vines that must be guided and woven to unlock",
    "alchemy circle lock, requiring the correct arrangement of alchemical symbols",
    "time warp lock, with the mechanism activating during specific temporal distortions",
    "fire maze lock, needing the opener to navigate through a maze of fire barriers",
    "wind compass lock, aligning with the direction of the wind",
    "tide-based lock, aligning with the current tidal patterns",
    "runic lock, needing the correct runic sequence to be traced",
    "shadow clock lock, with the shadow of an object indicating the correct time to unlock",
    "solar beam lock, requiring mirrors to align and reflect sunlight onto the mechanism",
    "living statue lock, with statues that must be moved into specific positions",
    "alchemy cauldron lock, requiring the correct ingredients to be mixed in a cauldron",
    "heartbeat lock, with the mechanism activated by the touch of a living being's heartbeat",
    "gong lock, requiring specific gongs to be struck in the right order",
    "spiritual resonance lock, needing a specific frequency of spiritual energy to activate",
    "time crystal lock, requiring a crystal that is attuned to a specific point in time",
    "phase-shift lock, responding to the correct phase shift of an energy source",
    "levitating key lock, where a levitating key must be manipulated to unlock",
    "ancient artifact lock, requiring the use of a specific ancient artifact to activate",
    "geomagnetic lock, aligning with the Earth's magnetic field",
    "mystical hourglass lock, requiring sand to flow through an hourglass to unlock",
    "quantum lock, with the mechanism activated by the quantum state of particles",
    "holographic puzzle lock, requiring the manipulation of holographic projections",
    "time dilation lock, with the mechanism activated during time dilation events",
    "moonlit lake lock, with the chest needing to be submerged in moonlit water",
    "dimensional key lock, where the key must be inserted from a different dimension",
    "moon and star alignment lock, requiring the alignment of celestial bodies",
    "time-traveling lock, needing the chest to be taken back in time to unlock",
    "sound wave lock, with sound waves generating specific resonances to unlock",
    "crystalline chamber lock, requiring crystals to be placed in specific chambers",
    "lunar clock lock, aligning with the phases of the moon",
    "quantum entanglement lock, requiring entangled particles to unlock",
    "energy prism lock, needing beams of energy to pass through a prism to unlock",
    "dream realm lock, requiring the chest to be accessed in the realm of dreams",
    "synchronized clockwork lock, with gears needing to move in precise synchronization",
    "starlight constellation lock, requiring stars to align in specific constellations",
    "time crystal chamber lock, with crystals needing to be inserted in a chamber",
    "celestial alignment lock, requiring the alignment of planets and stars"
  ]
}
